[
    {
        "id": 1,
        "date": "Thu Dec 09 2021",
        "timestamp": 1639032852579,
        "isTask": true,
        "description": "one",
        "isStarred": true,
        "boards": [
            "My Board"
        ],
        "priority": 1,
        "inProgress": false,
        "isCanceled": false,
        "isComplete": true,
        "dueDate": 0,
        "passedTime": 60620,
        "lastStartTime": 0
    },
    {
        "id": 2,
        "date": "Thu Dec 09 2021",
        "timestamp": 1639033041326,
        "isTask": false,
        "description": "one",
        "isStarred": false,
        "boards": [
            "My Board"
        ]
    },
    {
        "id": 3,
        "date": "Thu Dec 09 2021",
        "timestamp": 1639033499388,
        "isTask": true,
        "description": "todotest",
        "isStarred": false,
        "boards": [
            "My Board"
        ],
        "priority": 3,
        "inProgress": false,
        "isCanceled": false,
        "isComplete": true,
        "dueDate": 0,
        "passedTime": 0,
        "lastStartTime": 0
    },
    {
        "id": 4,
        "date": "Thu Dec 09 2021",
        "timestamp": 1639033981582,
        "isTask": true,
        "description": "fix",
        "isStarred": false,
        "boards": [
            "My Board"
        ],
        "priority": 3,
        "inProgress": false,
        "isCanceled": false,
        "isComplete": false,
        "dueDate": 0,
        "passedTime": 0,
        "lastStartTime": 0
    },
    {
        "id": 5,
        "date": "Thu Dec 09 2021",
        "timestamp": 1639034081752,
        "isTask": true,
        "description": "sec",
        "isStarred": false,
        "boards": [
            "My Board"
        ],
        "priority": 1,
        "inProgress": false,
        "isCanceled": false,
        "isComplete": false,
        "dueDate": 0,
        "passedTime": 0,
        "lastStartTime": 0
    }
]